contextpilot/__init__.py
contextpilot/context_index/__init__.py
contextpilot/context_index/compute_distance_cpu.py
contextpilot/context_index/compute_distance_gpu.py
contextpilot/context_index/index_construction.py
contextpilot/context_index/tree_nodes.py
contextpilot/context_ordering/__init__.py
contextpilot/context_ordering/inter_scheduler.py
contextpilot/context_ordering/intra_ordering.py
contextpilot/pipeline/__init__.py
contextpilot/pipeline/components.py
contextpilot/pipeline/multi_turn.py
contextpilot/pipeline/rag_pipeline.py
contextpilot/retriever/__init__.py
contextpilot/retriever/bm25.py
contextpilot/retriever/faiss_embedding.py
contextpilot/retriever/mem0_retriever.py
contextpilot/retriever/pageindex_retriever.py
contextpilot/server/__init__.py
contextpilot/server/conversation_tracker.py
contextpilot/server/eviction_heap.py
contextpilot/server/http_client.py
contextpilot/server/http_server.py
contextpilot/server/live_index.py
contextpilot/server/metadata.py
contextpilot/utils/__init__.py
contextpilot/utils/eval_metrics.py
contextpilot/utils/prompt_generator.py
contextpilot/utils/tools.py
contextpilot-0.3.0.dist-info/licenses/LICENSE
contextpilot-0.3.0.dist-info/METADATA
contextpilot-0.3.0.dist-info/WHEEL
contextpilot-0.3.0.dist-info/top_level.txt
contextpilot-0.3.0.dist-info/RECORD
