Metadata-Version: 2.4
Name: contextpilot
Version: 0.3.0
Summary: Efficient Retrieval-Augmented Generation with Accuracy-Preserving Context Reuse
Author: Yinsicheng Jiang, Chivier Humber
License: Apache-2.0
Project-URL: Homepage, https://github.com/SecretSettler/ContextPilot
Project-URL: Repository, https://github.com/SecretSettler/ContextPilot
Project-URL: Issues, https://github.com/SecretSettler/ContextPilot/issues
Keywords: rag,llm,context-reuse,kv-cache,retrieval-augmented-generation
Classifier: Development Status :: 4 - Beta
Classifier: Intended Audience :: Developers
Classifier: Intended Audience :: Science/Research
Classifier: License :: OSI Approved :: Apache Software License
Classifier: Programming Language :: Python :: 3
Classifier: Programming Language :: Python :: 3.10
Classifier: Programming Language :: Python :: 3.11
Classifier: Programming Language :: Python :: 3.12
Classifier: Topic :: Scientific/Engineering :: Artificial Intelligence
Requires-Python: >=3.10
License-File: LICENSE
Requires-Dist: datasets
Requires-Dist: transformers
Requires-Dist: elasticsearch==8.18.1
Requires-Dist: aiohttp
Requires-Dist: ujson
Requires-Dist: scipy
Requires-Dist: fastapi[all]
Requires-Dist: cupy-cuda12x
Requires-Dist: pytest
Provides-Extra: dev
Requires-Dist: black; extra == "dev"
Requires-Dist: bumpver; extra == "dev"
Requires-Dist: isort; extra == "dev"
Requires-Dist: pip-tools; extra == "dev"
Requires-Dist: pytest; extra == "dev"
Requires-Dist: pytest-cov; extra == "dev"
Requires-Dist: ipython; extra == "dev"
Dynamic: license-file
